pyjoepegs/__init__.py
pyjoepegs/activities.py
pyjoepegs/base.py
pyjoepegs/collections.py
pyjoepegs/items.py
pyjoepegs/maker_orders.py
pyjoepegs/owners.py
pyjoepegs/pyjoepegs.py
pyjoepegs/sales.py
pyjoepegs/search.py
pyjoepegs/users.py
pyjoepegs-0.0.3.dist-info/LICENSE
pyjoepegs-0.0.3.dist-info/METADATA
pyjoepegs-0.0.3.dist-info/WHEEL
pyjoepegs-0.0.3.dist-info/top_level.txt
pyjoepegs-0.0.3.dist-info/RECORD
