Metadata-Version: 2.1
Name: pyjoepegs
Version: 0.0.3
Summary: client library for joepegs api
Home-page: https://github.com/ishtos/pyjoepegs
Author: ishtos
License: APACHE LICENSE, VERSION 2.0
Keywords: pyjoepegs,joepegs
Classifier: Programming Language :: Python
License-File: LICENSE
Requires-Dist: requests
